wxai_langchain/__init__.py
wxai_langchain/credentials.py
wxai_langchain/llm.py
wxai_langchain-0.0.4.dist-info/LICENSE
wxai_langchain-0.0.4.dist-info/METADATA
wxai_langchain-0.0.4.dist-info/WHEEL
wxai_langchain-0.0.4.dist-info/top_level.txt
wxai_langchain-0.0.4.dist-info/RECORD
