Metadata-Version: 2.1
Name: wxai-langchain
Version: 0.0.4
Summary: wxai-langchain enables the use of IBM watsonx.ai in LangChain projects. This is not supported by IBM.
Author-email: Cong Nguyen <cong.nguyen@au1.ibm.com>
Project-URL: source, https://github.com/rampadc/wxai-langchain
Project-URL: Homepage, https://github.com/rampadc/wxai-langchain
Keywords: watsonx.ai,wxai,langchain
Requires-Python: >=3.9
License-File: LICENSE
Requires-Dist: urllib3<2
Requires-Dist: requests>=2.31.0
Requires-Dist: pydantic<=1.10.10
Requires-Dist: langchain>=0.0.200
Requires-Dist: ibm_cloud_sdk_core>=3.16.7
Requires-Dist: aiohttp>=3.8.4
Requires-Dist: ibm-watson-machine-learning>=1.0.311
Provides-Extra: dev
Requires-Dist: python-dotenv>=1.0.0; extra == "dev"
Requires-Dist: datasets==2.11.0; extra == "dev"
